README.txt
setup.py
jsbundle/__init__.py
jsbundle/bundle.py
jsbundle/docs.py
jsbundle/jsmin.py
jsbundle.egg-info/PKG-INFO
jsbundle.egg-info/SOURCES.txt
jsbundle.egg-info/dependency_links.txt
jsbundle.egg-info/requires.txt
jsbundle.egg-info/top_level.txt
jsbundle.egg-info/zip-safe
test/test-this-nose.py